bcwalletx/__init__.py
bcwalletx/bc_utils.py
bcwalletx/bcwalletx.py
bcwalletx/cl_utils.py
bcwalletx/version_checker.py
bcwalletx-1.2.12.dist-info/DESCRIPTION.rst
bcwalletx-1.2.12.dist-info/METADATA
bcwalletx-1.2.12.dist-info/RECORD
bcwalletx-1.2.12.dist-info/WHEEL
bcwalletx-1.2.12.dist-info/entry_points.txt
bcwalletx-1.2.12.dist-info/metadata.json
bcwalletx-1.2.12.dist-info/top_level.txt
